{"submissionId":"cI61W6MFSACa9HQKD4kukQ","DRAWING_ADVANCED":0.0,"DRAWING_RAW_ADVANCED_COUNT":0.0,"DRAWING_RAW_COVERED_COUNT":2.0,"DRAWING_RAW_UNCOVERED_COUNT":0.0,"DRAWING_UNCOVERED":0.0,"DRAWING_USED":0.0,"LOOP_ASSESSMENT":0.0,"LOOP_RAW_SITUATION_COUNT":0.0,"LOOP_RAW_TYPE_COUNT":0.0,"LOOP_SITUATION_VARIETY":0.0,"LOOP_VARIETY":0.0,"MESSAGEPASSING_RATIO":1.0,"MESSAGEPASSING_RAW_GLOBAL_COUNT":0.0,"MESSAGEPASSING_RAW_PARAMETER_COUNT":1.0,"OO_CLASS_COUNT":0.986,"OO_RAW_CLASS_COUNT":2.0,"OO_RAW_SMELL_COUNT":0.0,"OO_SMELLS":1.0}